ecgai_logging/__init__.py
ecgai_logging/log_decorator.py
ecgai_logging-0.0.4.dist-info/LICENSE
ecgai_logging-0.0.4.dist-info/METADATA
ecgai_logging-0.0.4.dist-info/WHEEL
ecgai_logging-0.0.4.dist-info/top_level.txt
ecgai_logging-0.0.4.dist-info/RECORD
