Metadata-Version: 2.1
Name: ecgai-logging
Version: 0.0.4
Summary: Decorator function for function level logging
Home-page: https://github.com/Ecg-Ai-com/ecgai-logging
Author: Rob Clapham
Author-email: 
License: UNKNOWN
Project-URL: Bug Tracker, https://github.com/Ecg-Ai-com/ecgai-logging/issues
Platform: UNKNOWN
Classifier: Programming Language :: Python :: 3
Classifier: Development Status :: 3 - Alpha
Classifier: Intended Audience :: Developers
Classifier: Topic :: System :: Logging
Classifier: License :: OSI Approved :: GNU General Public License v3 or later (GPLv3+)
Classifier: Operating System :: OS Independent
Requires-Python: >=3.6
License-File: LICENSE
